pydist2/__init__.py
pydist2/custom_typing.py
pydist2/distance.py
pydist2-0.0.5.dist-info/AUTHORS.rst
pydist2-0.0.5.dist-info/LICENSE
pydist2-0.0.5.dist-info/METADATA
pydist2-0.0.5.dist-info/WHEEL
pydist2-0.0.5.dist-info/entry_points.txt
pydist2-0.0.5.dist-info/top_level.txt
pydist2-0.0.5.dist-info/RECORD
