Metadata-Version: 2.1
Name: pydist2
Version: 0.0.5
Summary: pydist2 is a library that provides a set of methods for calculating distances between observations.
Home-page: https://github.com/Harmouch101/pydist2
Author: Mahmoud Harmouch
Author-email: mahmoudddharmouchhh@gmail.com
License: MIT license
Keywords: pydist2
Platform: UNKNOWN
Classifier: Development Status :: 2 - Pre-Alpha
Classifier: Intended Audience :: Developers
Classifier: License :: OSI Approved :: MIT License
Classifier: Natural Language :: English
Classifier: Programming Language :: Python :: 3.7
Classifier: Programming Language :: Python :: 3.8
Requires-Python: >=3.7<4
Requires-Dist: numpy (>=1.18.1)
